st_audiorec/__init__.py
streamlit_audio_rec-0.0.1.dist-info/LICENCE
streamlit_audio_rec-0.0.1.dist-info/METADATA
streamlit_audio_rec-0.0.1.dist-info/WHEEL
streamlit_audio_rec-0.0.1.dist-info/top_level.txt
streamlit_audio_rec-0.0.1.dist-info/RECORD
