Metadata-Version: 2.1
Name: streamlit-audio-rec
Version: 0.0.1
Summary: Official PyPI Package for [steamlit-audio-recorder by stefanrmmr] Streamlit Custom Component that enables recording audio from the client's mic in apps that are deployed to the web. (via browser Media-API, REACT-based)
Home-page: https://github.com/stefanrmmr/streamlit-audio-recorder
Author: Stefan Rummer
Author-email: stefan.rummer@outlook.com
License: UNKNOWN
Platform: UNKNOWN
Requires-Python: >=3.7
License-File: LICENCE
Requires-Dist: streamlit (>=0.63)
